{
  "title": {
    "type": "string",
    "required": true,
    "default": "Plans",
    "description": "Main heading for the pricing section"
  },
  "subtitle": {
    "type": "string",
    "required": false,
    "default": "",
    "description": "Subtitle text below the main heading"
  },
  "plans": {
    "type": "array",
    "required": true,
    "default": [
      {
        "planName": "Basic",
        "description": "Perfect for personal projects and hobbyists.",
        "price": "0",
        "features": ["1 User", "1GB Storage", "Community Forum"],
        "buttonText": "Get Started",
        "buttonVariant": "secondary"
      },
      {
        "planName": "Team",
        "description": "Collaborate with your team on multiple projects.",
        "price": "49",
        "features": ["10 Users", "100GB Storage", "Email Support", "Shared Workspaces"],
        "buttonText": "Choose Team Plan",
        "isPopular": true,
        "buttonVariant": "primary"
      },
      {
        "planName": "Agency",
        "description": "Manage all your clients under one roof.",
        "price": "149",
        "features": ["Unlimited Users", "1TB Storage", "Dedicated Support", "Client Invoicing"],
        "buttonText": "Contact Us",
        "buttonVariant": "primary"
      }
    ],
    "description": "Array of pricing plans with details"
  },
  "showAnimatedBackground": {
    "type": "boolean",
    "required": false,
    "default": true,
    "description": "Whether to show the animated background gradient"
  }
}
